fastdem/__init__.py
fastdem/__main__.py
fastdem/fastdem.xlsx
fastdem-0.9.0.dist-info/entry_points.txt
fastdem-0.9.0.dist-info/METADATA
fastdem-0.9.0.dist-info/WHEEL
fastdem-0.9.0.dist-info/RECORD
